odoo/addons/stock_picking_kind/README.rst
odoo/addons/stock_picking_kind/__init__.py
odoo/addons/stock_picking_kind/__manifest__.py
odoo/addons/stock_picking_kind/hooks.py
odoo/addons/stock_picking_kind/i18n/es.po
odoo/addons/stock_picking_kind/i18n/fr.po
odoo/addons/stock_picking_kind/i18n/it.po
odoo/addons/stock_picking_kind/i18n/pt.po
odoo/addons/stock_picking_kind/i18n/pt_BR.po
odoo/addons/stock_picking_kind/i18n/stock_picking_kind.pot
odoo/addons/stock_picking_kind/models/__init__.py
odoo/addons/stock_picking_kind/models/stock_picking.py
odoo/addons/stock_picking_kind/readme/CONTRIBUTORS.md
odoo/addons/stock_picking_kind/readme/DESCRIPTION.md
odoo/addons/stock_picking_kind/static/description/icon.png
odoo/addons/stock_picking_kind/static/description/index.html
odoo/addons/stock_picking_kind/tests/__init__.py
odoo/addons/stock_picking_kind/tests/test_stock_picking_kind.py
odoo/addons/stock_picking_kind/views/stock_picking_views.xml
odoo_addon_stock_picking_kind-18.0.1.0.0.4.dist-info/METADATA
odoo_addon_stock_picking_kind-18.0.1.0.0.4.dist-info/WHEEL
odoo_addon_stock_picking_kind-18.0.1.0.0.4.dist-info/top_level.txt
odoo_addon_stock_picking_kind-18.0.1.0.0.4.dist-info/RECORD
